LICENSE
README.md
setup.cfg
setup.py
animeup/__init__.py
animeup.egg-info/PKG-INFO
animeup.egg-info/SOURCES.txt
animeup.egg-info/dependency_links.txt
animeup.egg-info/requires.txt
animeup.egg-info/top_level.txt
animeup/pipelines/__init__.py
animeup/pipelines/lcm_sd15.py
animeup/pipelines/lcm_sdxl.py
animeup/utils/__init__.py
animeup/utils/data_utils.py
animeup/utils/scheduler_list.py